{
  "source": "espn-golf-leaderboard",
  "fetchedAt": "2026-03-01T22:34:46.422Z",
  "count": 1431,
  "players": {
    "Zach Bauchou": "10030",
    "Chad Ramey": "10057",
    "Davis Riley": "10058",
    "Adam Schenk": "10372",
    "Frankie Capan III": "10469",
    "Eric Cole": "10522",
    "Matt Wallace": "10548",
    "Aaron Wise": "10577",
    "Matthieu Pavon": "10596",
    "Taylor Moore": "10664",
    "Kevin Streelman": "1077",
    "Cam Davis": "10863",
    "Aaron Rai": "10906",
    "Jimmy Stanger": "10990",
    "Austin Smotherman": "11056",
    "Carson Young": "11143",
    "Nicolai Højgaard": "11250",
    "Rasmus Højgaard": "11253",
    "Max McGreevy": "11383",
    "Rico Hoey": "11385",
    "Hank Lebioda": "11387",
    "Garrick Higgo": "11393",
    "Christo Lamprecht": "11395",
    "Doug Ghim": "11456",
    "Brandt Snedeker": "1222",
    "Camilo Villegas": "1264",
    "Dan Brown": "1407",
    "Webb Simpson": "1614",
    "Billy Horschel": "1651",
    "Justin Hicks": "199",
    "Charley Hoffman": "205",
    "Brice Garnett": "2283",
    "Matt Kuchar": "257",
    "Chris Kirk": "3449",
    "Brendon Todd": "3454",
    "Paul Waring": "3474",
    "Gary Woodland": "3550",
    "Rafael Campos": "3683",
    "Patton Kizzire": "3980",
    "Danny Willett": "4304",
    "Kristoffer Reitan": "4348470",
    "Kevin Yu": "4349547",
    "Kris Ventura": "4351896",
    "Alejandro Tosti": "4358081",
    "Patrick Fishburn": "4358083",
    "John VanDerLaan": "4361934",
    "Pontus Nyholm": "4375977",
    "Lee Hodges": "4404991",
    "Vince Whaley": "4408315",
    "Nico Echavarria": "4408316",
    "Jeffrey Kang": "4408318",
    "Danny Walker": "4408319",
    "Kevin Roy": "4408320",
    "Takumi Kanaya": "4410612",
    "Dylan Wu": "4423323",
    "Austin Eckroat": "4425898",
    "Michael Thorbjornsen": "4425904",
    "Steven Fisk": "4426182",
    "Matti Schmid": "4566443",
    "Sami Välimäki": "4585548",
    "Shane Lowry": "4587",
    "Chandler Phillips": "4587989",
    "Isaiah Salinda": "4589406",
    "Davis Thompson": "4602218",
    "Tom Kim": "4602673",
    "Chandler Blanchet": "4618114",
    "John Parry": "4671",
    "Ricky Castillo": "4691931",
    "S.H. Kim": "4698579",
    "Jesper Svensson": "4699329",
    "Keita Nakajima": "4699418",
    "Mac Meissner": "4791222",
    "Nick Dunlap": "4832046",
    "Harry Higgs": "4844",
    "Rasmus Neergaard-Petersen": "4858859",
    "Joe Highsmith": "4868733",
    "Michael Brennan": "4921329",
    "Jackson Suber": "4982182",
    "Kensei Hirata": "5075548",
    "A.J. Ewart": "5075652",
    "Adrien Dumont de Chassart": "5076011",
    "Ryan Gerard": "5076021",
    "William Mouw": "5076025",
    "Davis Chatfield": "5113338",
    "Gordon Sargent": "5139663",
    "Thorbjørn Olesen": "5140",
    "Sudarshan Yellamaraju": "5143175",
    "Karl Vilips": "5147097",
    "David Ford": "5150294",
    "Neal Shipley": "5209442",
    "Blades Brown": "5211425",
    "Luke Clanton": "5215039",
    "Johnny Keefer": "5217048",
    "Andrew Putnam": "5502",
    "Adam Hadwin": "5548",
    "Peter Malnati": "5692",
    "Chan Kim": "5724",
    "Emiliano Grillo": "5882",
    "Lanto Griffin": "5962",
    "Séamus Power": "6001",
    "Beau Hossler": "6011",
    "Joel Dahmen": "6196",
    "David Lipsky": "6701",
    "Brooks Koepka": "6798",
    "Mackenzie Hughes": "6931",
    "Stephan Jaeger": "6937",
    "Adrien Saddier": "6962",
    "Sam Ryder": "7001",
    "K.H. Lee": "7083",
    "Marcelo Rozo": "7120",
    "Zecheng Dou": "8889",
    "Keith Mitchell": "8906",
    "Ben Silverman": "8910",
    "Max Homa": "8973",
    "Daniel Berger": "9025",
    "Adam Svensson": "9127",
    "Mark Hubbard": "9143",
    "Justin Lower": "9144",
    "Haotong Li": "9221",
    "Christiaan Bezuidenhout": "9243",
    "Erik van Rooyen": "9364",
    "Alex Smalley": "9484",
    "Jordan Smith": "9506",
    "Tommy Aaron": "1",
    "George Zahringer": "1022",
    "Chris DiMarco": "105",
    "Stuart Appleby": "11",
    "David Duval": "115",
    "Steve Elkington": "121",
    "Ernie Els": "123",
    "Bob Estes": "125",
    "Nick Faldo": "127",
    "Brad Faxon": "128",
    "Ray Floyd": "137",
    "Doug Ford": "138",
    "Fred Funk": "152",
    "Jim Furyk": "153",
    "Sergio Garcia": "158",
    "Retief Goosen": "167",
    "Jay Haas": "181",
    "Padraig Harrington": "186",
    "Seve Ballesteros": "20",
    "Scott Hoch": "204",
    "Charles Howell III": "208",
    "John Huston": "212",
    "Toshi Izawa": "219",
    "Lee Janzen": "223",
    "Miguel Angel Jiménez": "224",
    "Shingo Katayama": "240",
    "Jerry Kelly": "243",
    "Bernhard Langer": "261",
    "Paul Lawrie": "265",
    "Tom Lehman": "268",
    "Justin Leonard": "269",
    "Peter Lonard": "277",
    "Davis Love III": "278",
    "Steve Lowery": "280",
    "Sandy Lyle": "281",
    "Jeff Maggert": "283",
    "Shigeki Maruyama": "289",
    "Rich Beem": "29",
    "Len Mattiace": "292",
    "Billy Mayfair": "296",
    "Scott McCarron": "298",
    "Rocco Mediate": "305",
    "Phil Mickelson": "308",
    "Larry Mize": "310",
    "Colin Montgomerie": "313",
    "Byron Nelson": "319",
    "Jack Nicklaus": "320",
    "Mark O'Meara": "325",
    "José María Olazábal": "329",
    "Arnold Palmer": "334",
    "Craig Parry": "337",
    "Craig Perks": "346",
    "Kenny Perry": "349",
    "Gary Player": "352",
    "Nick Price": "358",
    "Thomas Bjørn": "37",
    "Chris Riley": "372",
    "Loren Roberts": "374",
    "Eduardo Romero": "375",
    "Adam Scott": "388",
    "Vijay Singh": "392",
    "Jeff Sluman": "393",
    "Craig Stadler": "403",
    "Kevin Sutherland": "417",
    "Toru Taniguchi": "422",
    "Phil Tataurangi": "423",
    "David Toms": "429",
    "Kirk Triplett": "432",
    "Scott Verplank": "441",
    "Tom Watson": "449",
    "Mike Weir": "453",
    "Tiger Woods": "462",
    "Ian Woosnam": "463",
    "Fuzzy Zoeller": "468",
    "Robert Allenby": "5",
    "Jonathan Byrd": "508",
    "Niclas Fasth": "526",
    "Gay Brewer": "54",
    "Thomas Levet": "551",
    "Justin Rose": "569",
    "Tom Byrum": "64",
    "Ángel Cabrera": "65",
    "Michael Campbell": "67",
    "Chad Campbell": "68",
    "Pat Perez": "707",
    "John Rollins": "709",
    "Billy Casper": "73",
    "George Archer": "763",
    "Jack Burke, Jr.": "764",
    "Bob Goalby": "765",
    "Herman Keiser": "768",
    "K.J. Choi": "77",
    "Ricky Barnes": "801",
    "Ryan Moore": "809",
    "Tim Clark": "81",
    "Darren Clarke": "82",
    "Alejandro Larrazabal": "851",
    "Charles Coody": "88",
    "John Cook": "89",
    "Fred Couples": "91",
    "Ben Crenshaw": "94",
    "Hunter Mahan": "957",
    "James Driscoll": "109",
    "Joe Durant": "114",
    "Steve Flesch": "136",
    "Carlos Franco": "142",
    "Paul Azinger": "15",
    "Pierre Fulke": "151",
    "Aaron Baddeley": "16",
    "Dudley Hart": "188",
    "Mikko Ilonen": "213",
    "Steve Jones": "232",
    "Jonathan Kaye": "241",
    "Franklin Langham": "262",
    "Bob May": "295",
    "Notah Begay III": "30",
    "Greg Norman": "323",
    "Jesper Parnevik": "336",
    "Dennis Paulson": "342",
    "Chris Perry": "348",
    "Greg Puga": "361",
    "Jeff Quinney": "364",
    "Rory Sabbatini": "377",
    "Tom Scherrer": "382",
    "Sam Snead": "397",
    "Steve Stricker": "412",
    "Hal Sutton": "418",
    "D.J. Trahan": "431",
    "Grant Waite": "443",
    "Duffy Waldorf": "445",
    "Mark Brooks": "56",
    "Mark Calcavecchia": "66",
    "Greg Chalmers": "74",
    "Stewart Cink": "78",
    "José Coceres": "84",
    "Billy Andrade": "10",
    "Glen Day": "100",
    "Clark Dennis": "102",
    "John Douma": "108",
    "Jason Dufner": "110",
    "Scott Dunlap": "112",
    "Todd Fischer": "135",
    "Dan Forsman": "140",
    "George Frake II": "141",
    "Harrison Frazar": "144",
    "Jeff Freeman": "146",
    "Robert Gamez": "156",
    "Stephen Gangluff": "157",
    "Matt Gogel": "164",
    "Chris Gonzales": "166",
    "Paul Goydos": "173",
    "Mathias Gronberg": "177",
    "Briny Baird": "18",
    "Donnie Hammond": "185",
    "John Harris": "187",
    "Jeff Hart": "189",
    "Wesley Heffernan": "192",
    "Brian Henninger": "195",
    "Tim Herron": "198",
    "Gabriel Hjertstedt": "201",
    "Mike Hulbert": "210",
    "Hale Irwin": "216",
    "Tripp Isenhour": "217",
    "Jeff Barlow": "22",
    "Thongchai Jaidee": "222",
    "Brandt Jobe": "225",
    "Kevin Johnson": "229",
    "Scott Johnson": "231",
    "Peter Jordan": "234",
    "Anthony Kang": "239",
    "Skip Kendall": "245",
    "Tom Kite": "248",
    "Brad Klapprott": "249",
    "Ben Bates": "25",
    "Gary Koch": "250",
    "Joel Kribel": "256",
    "J.L. Lewis": "271",
    "Frank Lickliter II": "272",
    "John Maginnes": "284",
    "Joey Maxon": "294",
    "Jim McGovern": "302",
    "Shaun Micheel": "307",
    "Bryce Molder": "312",
    "Gary Nicklaus": "321",
    "Gary Orr": "331",
    "Carl Paulson": "343",
    "Corey Pavin": "344",
    "David Peoples": "345",
    "Tom Pernice Jr.": "347",
    "Tim Petrovic": "351",
    "Phillip Price": "359",
    "Dicky Pride": "360",
    "Brett Quigley": "363",
    "Charles Raulerson": "366",
    "Jarmo Sandelin": "378",
    "Ronnie Black": "38",
    "Marty Schiene": "383",
    "Kyle Blackman": "39",
    "Chris Smith": "395",
    "Mike Sposa": "399",
    "Michael Allen": "4",
    "Jay Don Blake": "41",
    "Esteban Toledo": "427",
    "Bob Tway": "436",
    "Jimmy Walker": "446",
    "Chris Wall": "447",
    "Lee Westwood": "455",
    "Mark Wiebe": "456",
    "Jay Williamson": "457",
    "Dean Wilson": "459",
    "Willie Wood": "461",
    "Richard Zokol": "469",
    "Olin Browne": "58",
    "Brandel Chamblee": "75",
    "Jess Daley": "96",
    "Chris Anderson": "972",
    "Robert Damron": "98",
    "Luke List": "1059",
    "Todd Hamilton": "1090",
    "Joakim Haeggman": "1255",
    "Austin Eaton III": "1387",
    "Mark Hensby": "197",
    "Trevor Immelman": "215",
    "Graeme McDowell": "301",
    "Joe Ogilvie": "327",
    "Rod Pampling": "335",
    "Nick O'Hern": "489",
    "Ben Curtis": "523",
    "David Howell": "537",
    "Freddie Jacobson": "540",
    "Stuart Wilson": "586",
    "Luke Donald": "601",
    "Ian Poulter": "619",
    "Zach Johnson": "686",
    "Stephen Ames": "7",
    "Bo Van Pelt": "712",
    "Paul Casey": "72",
    "Casey Wittenberg": "822",
    "Ryan Palmer": "962",
    "John Daly": "97",
    "Ted Purdy": "997",
    "Lee Rinker": "1013",
    "Sal Spallone": "1018",
    "Nick Dougherty": "1019",
    "Trip Kuehne": "1056",
    "Patrick Damron": "1075",
    "D.J. Brigman": "1175",
    "Tommy Armour III": "12",
    "David Oh": "1204",
    "Chris Nallen": "1208",
    "Eric Axley": "1247",
    "Spencer Levin": "1257",
    "Peter Hedblom": "1288",
    "Clinton Jensen": "1341",
    "Y.E. Yang": "1350",
    "Mike Ruiz": "1351",
    "Rob Rashell": "1360",
    "Euan Walters": "1361",
    "Kyle Willmann": "1392",
    "Will Collins": "1408",
    "Steve Conran": "1409",
    "David Denham": "1410",
    "Matt Every": "1411",
    "Stephen Gallacher": "1412",
    "Scott Gibson": "1413",
    "Peter Hanson": "1414",
    "Nickolas Jones": "1415",
    "Troy Kelly": "1416",
    "Jose-Filipe Lima": "1417",
    "Jonathan Lomas": "1418",
    "John Mallinger": "1419",
    "Josh McCumber": "1420",
    "Eric Meichtry": "1421",
    "John Merrick": "1422",
    "Michael Putnam": "1423",
    "Conrad Ray": "1424",
    "Pierre-Henri Soero": "1425",
    "Lee Williams": "1426",
    "Keiichiro Fukabori": "150",
    "Bill Glasson": "163",
    "Jason Gore": "168",
    "J.P. Hayes": "191",
    "J.J. Henry": "196",
    "Steve Allan": "2",
    "Craig Barlow": "21",
    "Ryuji Imada": "214",
    "Peter Jacobsen": "221",
    "Ian Leggatt": "267",
    "Arron Oberholser": "326",
    "Geoff Ogilvy": "328",
    "Jerry Smith": "396",
    "Omar Uresti": "438",
    "Nick Gilliam": "480",
    "Paul McGinley": "486",
    "Jim Benepe": "502",
    "Simon Dyson": "525",
    "Richard Green": "528",
    "Robert Karlsson": "544",
    "Søren Kjeldsen": "547",
    "Bart Bryant": "59",
    "Aaron Barber": "643",
    "Paul Claxton": "692",
    "Scott Parel": "810",
    "Carl Pettersson": "856",
    "David Hearn": "928",
    "Troy Matteson": "1041",
    "Kenneth Ferrie": "1085",
    "Hideto Tanihara": "1099",
    "Vaughn Taylor": "1185",
    "Johan Edfors": "1692",
    "Julien Guerrier": "1694",
    "John M. Kelly": "1781",
    "Richie Ramsay": "1782",
    "Casey Watabu": "1783",
    "Dave Womack": "1784",
    "Henrik Stenson": "576",
    "Jeev Milkha Singh": "629",
    "Lucas Glover": "676",
    "Brett Wetterich": "689",
    "Ben Crane": "693",
    "Bradley Dredge": "865",
    "Nick Watney": "1042",
    "J.B. Holmes": "1067",
    "Daniel Chopra": "1176",
    "Johnson Wagner": "1265",
    "Sean O'Hair": "1359",
    "Woody Austin": "14",
    "Richard Sterne": "1499",
    "Andres Romero": "1712",
    "Liang Wen-Chong": "1724",
    "Drew Weaver": "3475",
    "Martin Kaymer": "3670",
    "Prayad Marksaeng": "3687",
    "Michael Thompson": "3688",
    "Soren Hansen": "532",
    "Heath Slocum": "630",
    "Brian Bateman": "690",
    "John Senden": "710",
    "Boo Weekley": "713",
    "Bubba Watson": "780",
    "Anders Hansen": "847",
    "Scott Piercy": "1037",
    "Alastair Forsyth": "1086",
    "Gary Wolstenholme": "1102",
    "Steve Marino": "1170",
    "Jason Bohn": "1173",
    "Brian Kortan": "1180",
    "D.A. Points": "1196",
    "John Ellis": "1197",
    "Robert Garrigus": "1254",
    "Sean English": "1323",
    "Chris Stroud": "1352",
    "Peter Tomasulo": "1372",
    "Phillip Archer": "1437",
    "Oliver Wilson": "1506",
    "Scott Sterling": "1642",
    "Mathew Goggin": "165",
    "Andrew Svoboda": "1658",
    "Jarrod Lyle": "1698",
    "Anthony Kim": "1745",
    "Kyle Stanley": "1778",
    "Robert Dinwiddie": "1797",
    "Hunter Haas": "182",
    "Chris Devlin": "2140",
    "Andrew Dresser": "2171",
    "Philippe Gasnier": "2288",
    "Joey Lamielle": "2574",
    "Michael Letzig": "2603",
    "Dustin Johnson": "3448",
    "Ross Fisher": "3462",
    "Robert Gaus": "3514",
    "Derek Fathauer": "3577",
    "Rickie Fowler": "3702",
    "Charlie Beljan": "3777",
    "Yohann Benson": "3778",
    "Brian Bergstol": "3779",
    "Travis Bertoni": "3780",
    "Jeffrey Bors": "3781",
    "Garrett Chaussard": "3782",
    "Jay Choi": "3783",
    "Bobby Collins": "3784",
    "Jordan Cox": "3785",
    "Fernando Figueroa": "3786",
    "Jimmy Henderson": "3787",
    "Ross McGowan": "3788",
    "Artemio Murakami": "3789",
    "Michael Quagliano": "3790",
    "Kevin Silva": "3791",
    "Nick Taylor": "3792",
    "Kevin Tway": "3793",
    "Jeff Wilson": "3794",
    "Brad Bryant": "507",
    "Jon Mills": "650",
    "Patrick Sheehan": "762",
    "Jon Turcott": "842",
    "Mike Gilmore": "913",
    "Doug LaBelle II": "1057",
    "Peter Fowler": "1114",
    "Hennie Otto": "1120",
    "Anthony Wall": "1129",
    "Brendan Jones": "1256",
    "Yoshinobu Tsukada": "1295",
    "Barry Hume": "1304",
    "Thomas Aiken": "1436",
    "Gregory Bourdy": "1443",
    "Ariel Cañete": "1446",
    "Richard Finch": "1456",
    "Simon Khan": "1471",
    "David Frost": "148",
    "Graeme Storm": "1500",
    "Danny Chia": "1517",
    "Doug McGuigan": "1525",
    "Steve Webster": "1539",
    "Jeff Overton": "1564",
    "Jon Bevan": "1686",
    "Simon Wakefield": "1706",
    "Azuma Yano": "1749",
    "Pelle Edberg": "3461",
    "Chih-Bing Lam": "3466",
    "Ewan Porter": "3471",
    "Grégory Havret": "3477",
    "Brad Lamb": "3520",
    "Andrew Tampion": "3643",
    "Peter Appleyard": "3817",
    "Rohan Blizard": "3818",
    "Adam Blyth": "3819",
    "Gary Boyd": "3820",
    "Josh Cunliffe": "3821",
    "Jamie Elson": "3822",
    "Jean-Baptiste Gonnet": "3823",
    "Benjamin Hebert": "3824",
    "David Horsey": "3825",
    "Jamie Howarth": "3826",
    "Hiroshi Iwata": "3827",
    "Shintaro Kai": "3828",
    "Pablo Larrazábal": "3829",
    "Michio Matsumura": "3830",
    "Damien McGrane": "3831",
    "Alex Noren": "3832",
    "Angelo Que": "3833",
    "Reinier Saxton": "3834",
    "Thomas Sherreard": "3835",
    "Scott Strange": "3836",
    "Philip Walton": "3837",
    "Martin Wiegele": "3838",
    "Chris Wood": "3839",
    "David Smail": "394",
    "Jean Van de Velde": "439",
    "Alex Cejka": "512",
    "Tom Gillis": "804",
    "Kevin Stadler": "860",
    "Darren Fichardt": "868",
    "Peter Baker": "873",
    "James Kingston": "878",
    "Jyoti Randhawa": "1096",
    "Charl Schwartzel": "1097",
    "Parker McLachlin": "1259",
    "Louis Oosthuizen": "1293",
    "Jeff Martin": "1335",
    "Eric Manning": "1512",
    "Nicholas Thompson": "1586",
    "Brian Gay": "159",
    "Sonny Skinner": "1617",
    "Vince Jewell": "1636",
    "Sam Arnold": "1726",
    "Greg Kraft": "253",
    "Cliff Kresge": "255",
    "Scott Hebert": "3383",
    "Ryan Benzel": "3513",
    "Curt Sanders": "3701",
    "David Long": "3754",
    "Brad Dean": "3940",
    "Eric Dugas": "3941",
    "Frank Esposito, Jr.": "3942",
    "Jim Estes": "3943",
    "Kyle Flinton": "3944",
    "Bradley Martin": "3945",
    "Mark Brown": "4033",
    "Tim Thelen": "424",
    "Tim Weinhart": "452",
    "Don Yrene": "467",
    "Hiroyuki Fujita": "694",
    "Rick Leibovich": "723",
    "Ken Duke": "745",
    "Chez Reavie": "769",
    "George McNeill": "808",
    "Richard S. Johnson": "903",
    "Alan Morin": "917",
    "Charlie Wi": "925",
    "Scott Gutschewski": "1195",
    "Matt Jones": "1367",
    "Michael Sim": "1384",
    "Colby Beckstrom": "1400",
    "Richard Bland": "1441",
    "Gonzalo Fernandez-Castaño": "1455",
    "Jose Manuel Lara": "1473",
    "Jean-Francois Lucquin": "1477",
    "Francesco Molinari": "1483",
    "Bronson Burgoon": "1626",
    "Michael Welch": "1736",
    "Steve Conway": "1766",
    "Matt Bettencourt": "1920",
    "Ryan Blaum": "1935",
    "Martin Laird": "2571",
    "Mike Miles": "2725",
    "Cameron Beckman": "28",
    "Andrew McLardy": "303",
    "Andrew Parr": "3445",
    "Rory McIlroy": "3470",
    "James Nitties": "3521",
    "Alvaro Quiros": "3668",
    "Trevor Murphy": "3727",
    "Nathan Tyler": "3847",
    "Sangmoon Bae": "4015",
    "Courtland Lowe": "4052",
    "James Kamte": "4261",
    "Drew Kittleson": "4414",
    "Tyson Alexander": "4633",
    "Doug Batty": "4634",
    "Joshua Brock": "4635",
    "Clark Klaasen": "4637",
    "Ben Martin": "4638",
    "Matt Nagy": "4639",
    "Kyle Peterman": "4640",
    "Vaughn Snyder": "4641",
    "Ryan Spears": "4642",
    "Shawn Stefani": "4643",
    "Cameron Tringale": "4645",
    "Kaname Yokoo": "466",
    "David Erdy": "4661",
    "Scott Lewis": "4662",
    "Craig Bowden": "47",
    "Jeff Brehaut": "53",
    "Raphael Jacquelin": "541",
    "Cameron Yancey": "777",
    "Sean Farren": "912",
    "Darron Stiles": "984",
    "Nathan Smith": "1221",
    "Edoardo Molinari": "1527",
    "Kevin Na": "318",
    "Marc Leishman": "3351",
    "Ryo Ishikawa": "4047",
    "Matteo Manassero": "4574",
    "Yuta Ikeda": "4712",
    "Byeong Hun An": "5285",
    "Brad Benjamin": "5286",
    "Nathan Green": "529",
    "Bill Haas": "774",
    "Jason Allred": "1008",
    "Brian Davis": "1049",
    "Derek Lamely": "1276",
    "Paul Sheehan": "1294",
    "Terry Pilkadaris": "1491",
    "Matthew Richardson": "1530",
    "Brendon de Jonge": "1758",
    "Pablo Martin": "1768",
    "Kent Jones": "233",
    "Dan McCarthy": "2683",
    "Rhys Davies": "3314",
    "Daniel Summerhays": "3452",
    "Jim Herman": "3598",
    "Kenny Kim": "3613",
    "Travis Hampshire": "3802",
    "Erick Justesen": "4014",
    "Kent Eger": "4022",
    "Hugo León": "4138",
    "S.Y. Noh": "4267",
    "Gareth Maybin": "4268",
    "Ty Tryon": "434",
    "Rafael Echenique": "4386",
    "James Morrison": "4566",
    "Bobby Gates": "4590",
    "Morgan Hoffmann": "4781",
    "Blaine Peffley": "5030",
    "Rikard Karlberg": "5349",
    "Russell Henley": "5409",
    "Bennett Blakeman": "5498",
    "Alex Martin": "5499",
    "Kevin Phelan": "5500",
    "Jason Preeo": "5501",
    "Mark Silvers": "5503",
    "Hudson Swafford": "5504",
    "Scott Langley": "5506",
    "Jon Curran": "5513",
    "Rich Barcelo": "590",
    "Joseph Bramlett": "5902",
    "Erik Compton": "646",
    "Steve Wheatcroft": "673",
    "Deane Pappas": "706",
    "Arjun Atwal": "824",
    "Charles Warren": "996",
    "Jhonattan Vegas": "1030",
    "Peter Uihlein": "1674",
    "Jason Day": "1680",
    "Jin Jeong": "4116",
    "Kyung Kim": "4284",
    "Mark Wilson": "479",
    "Hideki Matsuyama": "5860",
    "David Chung": "5903",
    "Lion Kim": "5904",
    "David Lynn": "1092",
    "Nicolas Colsaerts": "1283",
    "Jamie Donaldson": "1451",
    "Thaworn Wiratchant": "1588",
    "Ted Potter Jr.": "2883",
    "Branden Grace": "4383",
    "Keegan Bradley": "4513",
    "George Coetzee": "5076",
    "Alan Dunbar": "5615",
    "John Huh": "5797",
    "John Peterson": "6064",
    "Michael Weaver": "6711",
    "Steven Fox": "7102",
    "T.J. Vogel": "7127",
    "Guan Tianlang": "7165",
    "Geoffrey Sisk": "1066",
    "Roger Tambellini": "1184",
    "Marcel Siem": "1336",
    "Marcus Fraser": "1457",
    "Josh Teater": "1568",
    "Jaco Van Zyl": "1762",
    "Edward Loar": "276",
    "Ryan Yip": "3372",
    "Scott Stallings": "3378",
    "Matt Harmon": "3384",
    "Brendan Steele": "3596",
    "Brian Stuard": "3599",
    "Alistair Presnell": "3676",
    "Jesse Smith": "3704",
    "Kevin Chappell": "3857",
    "Brandon Brown": "4016",
    "Tano Goya": "4244",
    "John Nieporte": "4245",
    "Chris Doak": "4335",
    "Russell Knox": "4483",
    "Randall Hutchison": "4784",
    "Ryan Nelson": "4927",
    "Grayson Murray": "5462",
    "Jordan Spieth": "5467",
    "David Lingmerth": "5574",
    "Brandon Crick": "5617",
    "Gavin Hall": "5663",
    "Bio Kim": "5821",
    "C.T. Pan": "6017",
    "Junggon Hwang": "6042",
    "Luke Guthrie": "6066",
    "Steven Alker": "660",
    "Morten Ørum Madsen": "6628",
    "Eddie Pepperell": "6629",
    "Harold Varner III": "6991",
    "Ryan Sullivan": "7087",
    "Zack Fischer": "7158",
    "Yui Ueda": "8959",
    "Matt Weibring": "897",
    "John Hahn": "8972",
    "Michael Kim": "8974",
    "Cory McElyea": "8987",
    "Steven Bowditch": "1112",
    "Graham DeLaet": "2127",
    "Roberto Castro": "3740",
    "Jonas Blixt": "3856",
    "Joost Luiten": "4831",
    "Victor Dubuisson": "5402",
    "Harris English": "5408",
    "Patrick Reed": "5579",
    "Derek Ernst": "7004",
    "Oliver Goss": "7015",
    "Garrick Porteous": "9028",
    "Matt Fitzpatrick": "9037",
    "Michael McCoy": "9056",
    "Jordan Niebrugge": "9402",
    "Chang-woo Lee": "9409",
    "Brian Harman": "1225",
    "Bernd Wiesberger": "4317",
    "Anirban Lahiri": "4989",
    "James Hahn": "5025",
    "Robert Streb": "5619",
    "Corey Conners": "9126",
    "Bradley Neil": "9588",
    "Antonio Murdaca": "9822",
    "Gunn Yang": "9844",
    "Byron Meth": "9845",
    "Matias Dominguez": "9930",
    "Scott Harvey": "9942",
    "Jared Becher": "10044",
    "Rich Berberian Jr.": "10045",
    "Bryson DeChambeau": "10046",
    "Cole Hammer": "10047",
    "Nick Hardy": "10048",
    "Sam Horsfield": "10049",
    "Kyle Jones": "10050",
    "Alex Kim": "9625",
    "Matt Mabrey": "10052",
    "Jack Maguire": "10053",
    "Denny McCarthy": "10054",
    "Lee McCoy": "10055",
    "Pat Wilson": "10059",
    "Tjaart van der Walt": "1186",
    "Brad Elder": "120",
    "Brad Fritsch": "147",
    "Shiv Kapur": "1583",
    "Billy Hurley III": "1612",
    "Sam Saunders": "1613",
    "Jamie Lovemark": "1676",
    "Tony Finau": "2230",
    "Kevin Kisner": "2552",
    "Garth Mulroy": "3228",
    "Kurt Barnes": "3647",
    "Danny Lee": "3950",
    "Marc Warren": "4276",
    "Andy Pope": "4827",
    "Tommy Fleetwood": "5539",
    "Shunsuke Sonoda": "5556",
    "Jason Palmer": "5726",
    "Josh Persons": "5744",
    "Seuk-Hyun Baek": "5795",
    "WC Liang": "5862",
    "Andy Sullivan": "5956",
    "Alexander Levy": "6041",
    "Blayne Barber": "6062",
    "Tom Hoge": "6086",
    "Richard H. Lee": "6644",
    "Matt NeSmith": "6954",
    "Tim O'Neal": "770",
    "Michael Davan": "8903",
    "Cody Gribble": "8971",
    "Cameron Smith": "9131",
    "Masahiro Kawamura": "9220",
    "Jimmy Gunn": "9271",
    "Oliver Farr": "9468",
    "Brian Campbell": "9525",
    "Sebastian Cappelen": "9564",
    "Ollie Schniederjans": "9568",
    "Tyler Duncan": "9569",
    "Lucas Bjerregaard": "9575",
    "Brandon Hagy": "9584",
    "Kevin Lucas": "9597",
    "Jake Knapp": "9843",
    "Romain Langasque": "10099",
    "Derek Bard": "10445",
    "Paul Chaplet": "10446",
    "Sammy Schmitz": "10447",
    "Fabián Gómez": "3375",
    "Troy Merritt": "3970",
    "Rafa Cabrera Bello": "4321",
    "Justin Thomas": "4848",
    "Kiradech Aphibarnrat": "5771",
    "Cheng Jin": "8900",
    "Smylie Kaufman": "9528",
    "Scott Fernandez": "10225",
    "Clément Sordet": "10230",
    "Stefano Mazzoli": "10231",
    "Soomin Lee": "10310",
    "Paul Howard": "10569",
    "Yosuke Tsukada": "10605",
    "Oskar Arvidsson": "10628",
    "Scott Gregory": "10629",
    "Shugo Imahira": "10630",
    "Scott Hend": "1178",
    "Robert Rock": "1494",
    "Colt Knost": "1793",
    "Dave Coupland": "3459",
    "William McGirt": "3532",
    "Kodai Ichihara": "4318",
    "James Heath": "4619",
    "Nick Cullen": "5007",
    "Lasse Jensen": "5303",
    "Tyrrell Hatton": "5553",
    "Andrew Johnston": "5838",
    "Matthew Southgate": "5852",
    "Kristoffer Broberg": "6100",
    "Jack Senior": "6221",
    "Haydn Porteous": "6278",
    "Brandon Stone": "6280",
    "Sanghee Lee": "6734",
    "Zander Lombard": "7056",
    "Kyung-tae Kim": "8858",
    "Thomas Pieters": "9031",
    "Satoshi Kodaira": "9076",
    "Nathan Holman": "9199",
    "Callum Shinkwin": "9258",
    "Paul Dunne": "9589",
    "Ryan Evans": "9743",
    "Yusaku Miyazato": "978",
    "Jon Rahm": "9780",
    "Phachara Khongwatmai": "9852",
    "Jeunghun Wang": "9854",
    "Marco Dawson": "99",
    "Brad Dalke": "10488",
    "Curtis Luck": "10910",
    "Toto Gana": "10999",
    "Stewart Hagestad": "11000",
    "Si Woo Kim": "7081",
    "Austin Connelly": "10017",
    "Xander Schauffele": "10140",
    "Julian Suri": "10195",
    "Luca Cianchetti": "10227",
    "Wesley Bryan": "10360",
    "Sebastián Muñoz": "10404",
    "Young-han Song": "10422",
    "Mark Foster": "1087",
    "Connor Syme": "10983",
    "Adam Hodkinson": "11147",
    "Haydn McCullen": "11148",
    "Harry Ellis": "11174",
    "Yikeun Chang": "11175",
    "Ashley Hall": "11176",
    "Alfie Plant": "11177",
    "Paul Broadhurst": "1280",
    "David Drysdale": "1453",
    "Stuart Manley": "1478",
    "Adam Bland": "1688",
    "Fabrizio Zanotti": "1770",
    "Andrew Dodt": "3639",
    "Matthew Griffin": "4219",
    "Ryan Fox": "4251",
    "Michael Hendry": "4252",
    "Mike Lorenzo-Vera": "4272",
    "Sung Kang": "4449",
    "Jbe Kruger": "4993",
    "Shaun Norris": "5057",
    "Dylan Frittelli": "5167",
    "Laurie Canter": "5550",
    "Nick McCarthy": "5827",
    "Kent Bulle": "6180",
    "Gi-Whan Kim": "6706",
    "Joe Dean": "6970",
    "Ryan McCarthy": "7026",
    "Alexander Björk": "9469",
    "Maverick McNealy": "9530",
    "Toby Tree": "9821",
    "Calum Hill": "10102",
    "Garrett Rank": "10165",
    "Lucas Herbert": "10343",
    "David Gazzolo": "10362",
    "Philip Barbaree, Jr.": "10563",
    "Braden Thornberry": "11094",
    "Dylan Meyer": "11115",
    "Sungjae Im": "11382",
    "Tyler Strafaci": "11447",
    "Matt Parziale": "11457",
    "Tim Wilkinson": "1157",
    "Michael Miller": "2732",
    "Michael Block": "3312",
    "Jason Scrivener": "4265",
    "David Bransdon": "4306",
    "Noah Goodwin": "4339409",
    "Shintaro Ban": "4349524",
    "Jacob Bergeron": "4349535",
    "Luis Gagne": "4349536",
    "Franklin Huang": "4349539",
    "Theo Humphrey": "4349541",
    "Ryan Lumsden": "4349542",
    "Rhett Rasmussen": "4349543",
    "Timothy Wiseman": "4349544",
    "Chris Andrew Babcock": "4349548",
    "Cole Miller": "4349563",
    "Sulman Raza": "4349564",
    "Shota Akiyoshi": "4349587",
    "Mickey DeMorat": "4349592",
    "Rikuya Hoshino": "4350033",
    "Wen-Chong Liang": "5209",
    "Chesson Hadley": "5704",
    "Dean Burmester": "5830",
    "Tom Lewis": "5868",
    "Patrick Cantlay": "6007",
    "Sebastián Vázquez": "6034",
    "Patrick Rodgers": "6825",
    "Chris Naegel": "8876",
    "Michael Hebert": "9272",
    "Sung Joon Park": "9277",
    "Will Grimmer": "9527",
    "Cameron Wilson": "9532",
    "Trey Mullinax": "9626",
    "Richy Werenski": "9804",
    "Will Zalatoris": "9877",
    "Shubhankar Sharma": "9888",
    "Sam Burns": "9938",
    "J.J. Spaun": "10166",
    "Sean McCarty": "1062",
    "Joaquín Niemann": "11099",
    "Jaysen Hansen": "11218",
    "Seung-su Han": "1132",
    "Ryan Armour": "1750",
    "Brian Smock": "3262",
    "Ryan Vermeer": "3284",
    "Jason Kokrak": "3317",
    "Johan Kok": "3541",
    "Matthew Borchert": "3707",
    "Jason Schmuhl": "4213",
    "Ryuko Tokimatsu": "4357758",
    "Ben Kern": "4372513",
    "Shawn Warren": "4372514",
    "Mikko Korhonen": "4374",
    "Scott Brown": "4591",
    "Andrew Landry": "4682",
    "Jorge Campillo": "4691",
    "Danny Balin": "5670",
    "Marty Jertson": "5769",
    "Justin Harding": "5825",
    "Adrian Otaegui": "5965",
    "Bob Sowards": "631",
    "Craig Hocknull": "6608",
    "Kelly Kraft": "6689",
    "Matt Dobyns": "6899",
    "Whee Kim": "7082",
    "Zach J. Johnson": "9074",
    "David Muttitt": "9099",
    "Austin Cook": "9517",
    "Alvaro Ortiz": "10481",
    "Jovan Rebula": "10944",
    "Viktor Hovland": "4364873",
    "Devon Bling": "4420723",
    "Kevin O'Connell": "5662",
    "Adam Long": "6015",
    "Charlie Danielson": "10442",
    "Collin Morikawa": "10592",
    "Andreas Halvorsen": "11188",
    "Adri Arnaus": "11350",
    "Callum Tarren": "11376",
    "Lee Slattery": "1498",
    "Nate Lashley": "1600",
    "Rob Oppenheim": "1733",
    "Alex Prugh": "3322",
    "Justin Walters": "4008",
    "Brandon Wu": "4355673",
    "Chip McDaniel": "4362864",
    "Eric Dietrich": "4425896",
    "Chandler Eaton": "4425897",
    "Daniel Hillier": "4425899",
    "Mikumu Horikawa": "4425900",
    "Matt Naumec": "4425901",
    "Noah Norton": "4425902",
    "Hayden Shieh": "4425903",
    "Spencer Tibbits": "4425905",
    "Cameron Young": "4425906",
    "Merrick Bremner": "5082",
    "Julián Etulain": "5259",
    "Carlos Ortiz": "5532",
    "Rhys Enoch": "6776",
    "Connor Arendell": "6781",
    "Renato Paratore": "6979",
    "Sepp Straka": "8961",
    "Zac Blair": "9040",
    "Abraham Ancer": "9261",
    "Scottie Scheffler": "9478",
    "Marcus Kinhult": "9496",
    "Brett Drewitt": "9791",
    "Mito Pereira": "9931",
    "Yuxin Lin": "10493",
    "J.T. Poston": "10505",
    "Cameron Champ": "11098",
    "Victor Perez": "11340",
    "Matthew Wolff": "4412121",
    "John Augenstein": "4421475",
    "James Sugrue": "4566449",
    "Andy Ogletree": "4683804",
    "Lukas Michel": "4691932",
    "Abel Gallegos": "4701571",
    "Jazz Janewattananond": "9413",
    "Kurt Kitayama": "10364",
    "Paul Barjon": "10831",
    "Sandy Scott": "11149",
    "Greyson Sigg": "11333",
    "Robert MacIntyre": "11378",
    "Preston Summerhays": "4565481",
    "Eduard Rousaud": "4690741",
    "John Pak": "4691933",
    "Thomas Detry": "4837",
    "Matthias Schwab": "5729",
    "JC Ritchie": "9374",
    "Taylor Pendrith": "9658",
    "Wyndham Clark": "11119",
    "Alex Beach": "11219",
    "Doc Redman": "11448",
    "Rob Labritz": "259",
    "John O'Leary": "3516",
    "Alex Knoll": "3524",
    "Ken Tanigawa": "421",
    "Justin Bertsch": "4420096",
    "Ben Cook": "4422368",
    "Xinjun Zhang": "4479",
    "Michael Auterson": "4687089",
    "Bud Cauley": "5338",
    "Judd Gibb": "5551",
    "Rod Perry": "667",
    "Jason Caron": "802",
    "Jeff Roth": "906",
    "Talor Gooch": "9513",
    "Charles Osborne": "4567806",
    "Joe Long": "4705886",
    "Carson Schaake": "10129",
    "Johannes Veerman": "10186",
    "Hayden Springer": "10562",
    "Chris Crawford": "10576",
    "Justin Suh": "10583",
    "Adrian Meronk": "10839",
    "Sahith Theegala": "10980",
    "Kyle Westmoreland": "11105",
    "Zach Zaback": "11120",
    "Brad Kennedy": "1470",
    "Wade Ormsby": "1489",
    "Hayden Buckley": "4364752",
    "Taylor Montgomery": "4372851",
    "Wilson Furr": "4399279",
    "Wilco Nienaber": "4408396",
    "Akshay Bhatia": "4419142",
    "Yosuke Asaji": "4566423",
    "Chris Baker": "4628",
    "Spencer Ralston": "4683972",
    "Zack Sucher": "4708",
    "Bo Hoag": "4780",
    "Pierceson Coody": "4837368",
    "Mario Carmona": "4868729",
    "Roy Martin Cootes": "4868730",
    "Luis Fernando Fernando Barco": "4868731",
    "James Paul Hervol": "4868732",
    "Matt Sharpstene": "4868734",
    "Davis Shore": "4868735",
    "Michael Johnson": "5765",
    "Guido Migliozzi": "9474",
    "Robby Shelton": "9531",
    "Rick Lamb": "9691",
    "Andrew Kozan": "9907",
    "Marcus Armitage": "9928",
    "Min Woo Lee": "4410932",
    "Laird Shepherd": "4872730",
    "James Piot": "4950408",
    "Austin Greaser": "5016071",
    "Aaron Jarvis": "5016110",
    "Paul Dickinson": "103",
    "Kramer Hickok": "10363",
    "Wyatt Worthington II": "10668",
    "Ryan Brehm": "1548",
    "Jesse Mueller": "2767",
    "Yuki Inamori": "4399256",
    "Sadom Kaewkanjana": "4422196",
    "Jinichiro Kozuma": "4594413",
    "Ryosuke Kinoshita": "4699314",
    "Kyle Mendoza": "4713444",
    "Tyler Collet": "4723205",
    "Brandon Bingaman": "5070299",
    "Tim Feenstra": "5070300",
    "Austin Hurt": "5070301",
    "Colin Inglis": "5070302",
    "Nic Ishee": "5070303",
    "Jared Jones": "5070304",
    "Dylan Newman": "5070305",
    "Zac Oakley": "5070306",
    "Casey Pyne": "5070307",
    "Oliver Bekker": "5097",
    "Daniel van Tonder": "5857",
    "Yannik Paul": "10060",
    "Brandon Matthews": "11074",
    "Sean Crocker": "11110",
    "Andrew Novak": "11332",
    "Charlie Reiter": "11398",
    "Fran Quinn": "3237",
    "Wil Besseling": "4313",
    "Sam Stevens": "4426181",
    "Harry Hall": "4589438",
    "Richard Mansell": "4684823",
    "Chris Gotterup": "4690755",
    "Luke Gannon": "4690756",
    "Tomoyasu Sugiyama": "4699308",
    "Daijiro Izumida": "4699356",
    "Sam Bennett": "4791221",
    "Caleb Manuel": "4869419",
    "Matt McCarty": "4901368",
    "Jediah Morgan": "4914977",
    "Andrew Beckler": "5076005",
    "Fred Biondi": "5076006",
    "Brady Calkins": "5076007",
    "Keith Greene": "5076022",
    "Ben Lorenz": "5076023",
    "Maxwell Moldovan": "5076024",
    "Travis Vick": "5076036",
    "Erik Barnes": "5557",
    "Marcel Schneider": "6031",
    "Roger Sloan": "6090",
    "Kalle Samooja": "7055",
    "MJ Daffue": "7110",
    "Sean Jacklin": "7119",
    "Chase Seiffert": "8975",
    "Sebastian Söderberg": "9494",
    "Todd Sinnott": "9897",
    "John Catlin": "10687",
    "Jamie Rutherford": "10913",
    "Anthony Quayle": "11235",
    "Stephen Dodd": "1519",
    "Sihwan Kim": "3861",
    "Matthew Jordan": "4390719",
    "Marco Penge": "4585549",
    "Kazuki Higa": "4597553",
    "Justin De Los Santos": "4699389",
    "Yuto Katsuragawa": "4699414",
    "Jack Floydd": "4701539",
    "Sam Bairstow": "4872728",
    "Filippo Celli": "4884239",
    "Minkyu Kim": "4896418",
    "David Carey": "4897394",
    "Barclay Brown": "5080434",
    "Mingyu Cho": "5080435",
    "Ronan Mullarney": "5080437",
    "Aldrich Potgieter": "5080439",
    "Alex Wrigley": "5080440",
    "David Law": "5547",
    "Matt Ford": "5836",
    "Ben Campbell": "7011",
    "Jorge Fernández Valdés": "7156",
    "Lars Van Meijel": "9168",
    "Dimi Papadatos": "9197",
    "Thriston Lawrence": "9240",
    "Ashley Chesters": "9577",
    "Scott Vincent": "9963",
    "Harrison Crowe": "4997160",
    "Ben Carr": "5132256",
    "Mateo Fernández de Oliveira": "5139661",
    "Matthew McClean": "5139662",
    "Simon Forsström": "10020",
    "Corey Pereira": "10138",
    "Kyle Mueller": "10574",
    "Brent Grant": "10941",
    "Jordan Gumberg": "11243",
    "Alejandro Del Rey": "11465",
    "Berry Henson": "3483",
    "Alex Schaake": "4362028",
    "Deon Germishuys": "4408387",
    "David Nyfjall": "4575904",
    "Patrick Cover": "4612976",
    "Ryutaro Nagano": "4699375",
    "Vincent Norrman": "4868296",
    "David Puig": "4895429",
    "J.J. Grey": "4904294",
    "Jacob Solomon": "5113334",
    "Wenyi Ding": "5119683",
    "Omar Morales": "5143188",
    "Bastien Amat": "5147093",
    "Christian Cavaliere": "5147094",
    "Isaac Simmons": "5147095",
    "Brendan Valdes": "5147096",
    "Alexander Yang": "5147098",
    "Jens Dantorp": "6103",
    "Paul Haley II": "6607",
    "Jesse Schutte": "6611",
    "Gunn Charoenkul": "7047",
    "Olin Browne Jr.": "9287",
    "Austen Truslow": "9379",
    "Ewen Ferguson": "10838",
    "Taichi Kho": "11334",
    "Travis Smyth": "11345",
    "Kyle Barker": "11352",
    "Martin Rohwer": "11372",
    "Alejandro Cañizares": "1763",
    "Hurly Long": "4352363",
    "Alex Fitzpatrick": "4364865",
    "David Micheluzzi": "4368975",
    "Ben Griffin": "4404992",
    "Antoine Rozner": "4407372",
    "Kyungnam Kang": "4448",
    "Brandon Robinson Thompson": "4663355",
    "Haydn Barron": "4699413",
    "Taiga Semikawa": "5077279",
    "Dan Bradbury": "5081630",
    "Michael Stewart": "5102587",
    "Connor McKinney": "5118372",
    "Seungsu Han": "5143183",
    "Tiger Christensen": "5146173",
    "Kazuki Yasumori": "5146556",
    "Josele Ballester": "5152205",
    "Alex Maguire": "5152206",
    "Gunner Wiebe": "5220",
    "Ockie Strydom": "6485",
    "Nacho Elvira": "7169",
    "Graeme Robertson": "9156",
    "Ben Taylor": "10134",
    "Tom Whitney": "10177",
    "Wil Bateman": "10358",
    "Ryan McCormick": "10591",
    "Jared du Toit": "10666",
    "Kevin Dougherty": "10929",
    "Max Greyserman": "11101",
    "Trace Crowe": "11183",
    "Harrison Endycott": "11342",
    "Stuart Macdonald": "11362",
    "David Skinns": "3257",
    "Richard T. Lee": "4036",
    "Aaron Cockerill": "4407520",
    "Matthew Anderson": "4425875",
    "Michael Blair": "4425881",
    "Alistair Docherty": "4425907",
    "Raul Pereda": "4643737",
    "Parker Coody": "4697379",
    "Ryo Hisatsune": "4858572",
    "Michael Gligic": "4859",
    "Myles Creighton": "4870468",
    "Max Sear": "4915906",
    "Étienne Papineau": "4918119",
    "Jacob Bridgeman": "5054388",
    "Sam Choi": "5153579",
    "Jakob Chicoyne": "5214380",
    "Ashton McCulloch": "5214381",
    "Jake Lane": "5214382",
    "Marc-Olivier Plasse": "5214383",
    "Justin Matthews": "5214384",
    "Cam Kellett": "5214385",
    "Henrik Norlander": "5573",
    "Martin Trainer": "6151",
    "Kevin Stinson": "9662",
    "Carl Yuan": "9951",
    "Ludvig Åberg": "4375972",
    "Jackson Koivun": "5215013",
    "Otto Black": "10715",
    "Michael McGowan": "11381",
    "Tom McKibbin": "4348444",
    "Willie Mack III": "4355611",
    "Tim Widing": "4375973",
    "Chris Petefish": "4422179",
    "Eugenio Chacarra": "4565467",
    "Casey Jarvis": "4610056",
    "Riki Kawamoto": "4699407",
    "Taisei Shimizu": "4699422",
    "Logan McAllister": "5007905",
    "Santiago de la Fuente": "5044433",
    "Ben James": "5077389",
    "Joey Vrzich": "5125010",
    "Frederik Kjettrup": "5149776",
    "Parker Bell": "5214990",
    "Bryan Kim": "5214991",
    "Hiroshi Tai": "5214992",
    "Gunnar Broin": "5215037",
    "Jackson Buchanan": "5215038",
    "Colin Prater": "5215040",
    "Wells Williams": "5215041",
    "John Chin": "5567",
    "Carter Jenkins": "6000",
    "Ben Kohles": "6922",
    "Grant Forrest": "6958",
    "Evan Beck": "10559",
    "Justin Hastings": "5203536",
    "Noah Kent": "5276688",
    "Eric Steger": "10184",
    "Jesse Droemer": "11481",
    "Tom Johnson": "1752",
    "Niklas Norgaard": "4382434",
    "John Somers": "4612290",
    "Michael Kartrude": "4693951",
    "Elvis Smylie": "4714133",
    "Larkin Gross": "4845305",
    "Greg Koch": "4845307",
    "Andre Chi": "5275498",
    "Rupe Taylor": "5280927",
    "Ryan Lenahan": "9620",
    "Trevor Cone": "10933",
    "Frederic LaCroix": "4592246",
    "James Nicholas": "4683800",
    "Chase Johnson": "4683964",
    "George Kneiser": "4686084",
    "Cameron Tankersley": "4832045",
    "Kevin Velo": "5007595",
    "Trent Phillips": "5075306",
    "Yuta Sugiura": "5109769",
    "Emilio González": "5113335",
    "Joey Herrera": "5158295",
    "Will Chandler": "5210224",
    "Trevor Gutschewski": "5223200",
    "Riley Lewis": "5258813",
    "George Duangmanee": "5281166",
    "Harrison Ott": "5282713",
    "Mason Howell": "5289811",
    "Michael La Sasso": "5289812",
    "Bryan Lee": "5289813",
    "Zachery Pollo": "5289814",
    "Lance Simpson": "5289815",
    "Matt Vogt": "5289816",
    "Tyler Weaver": "5289817",
    "Grant Haefner": "5289818",
    "Frankie Harris": "5289828",
    "Andrea Pavan": "5423",
    "Joakim Lagergren": "5727",
    "Roberto Díaz": "6783",
    "Jacques Kruyswijk": "7072",
    "John Axelsen": "10190",
    "Daniel Brown": "10221",
    "Daniel Young": "10382",
    "Oliver Lindell": "10770",
    "Nathan Kimsey": "10914",
    "Angel Hidalgo": "11469",
    "Ryan Peake": "3961761",
    "Curtis Knipes": "4566630",
    "Jesper Sandborg": "4608562",
    "George Bloor": "4693053",
    "Mikiya Akutsu": "4699294",
    "OJ Farrell": "4868351",
    "Bryan Newman": "4900733",
    "Martin Couvra": "5102625",
    "Jacob Skov Olesen": "5217198",
    "Sampson Zheng": "5223866",
    "Ryggs Johnston": "5236241",
    "Cameron Adam": "5293230",
    "Sebastian Cave": "5293231",
    "Ethan Fang": "5293232",
    "Connor Graham": "5293233",
    "Filip Jakubcik": "5293234",
    "Frazer Jones": "5293235",
    "Richard Teder": "5293236",
    "Dylan Naidoo": "9894",
    "Ludvig Aberg": "50525"
  }
}